pykuvien/__init__.py
pykuvien-1.0.2.dist-info/DESCRIPTION.rst
pykuvien-1.0.2.dist-info/METADATA
pykuvien-1.0.2.dist-info/RECORD
pykuvien-1.0.2.dist-info/WHEEL
pykuvien-1.0.2.dist-info/metadata.json
pykuvien-1.0.2.dist-info/top_level.txt
sample/__init__.py
