Metadata-Version: 2.0
Name: pykuvien
Version: 1.0.2
Summary: Python library for interacting with the kuvien.io API
Home-page: https://github.com/Kelwing/pykuvien
Author: Kuvien Dev Team
Author-email: kelwing@kuvien.io
License: UNKNOWN
Keywords: kuvien api images
Platform: UNKNOWN
Classifier: Development Status :: 4 - Beta
Classifier: Intended Audience :: Developers
Classifier: Topic :: Software Development :: Libraries
Classifier: License :: OSI Approved :: MIT License
Classifier: Programming Language :: Python :: 2
Classifier: Programming Language :: Python :: 2.7
Classifier: Programming Language :: Python :: 3
Classifier: Programming Language :: Python :: 3.4
Classifier: Programming Language :: Python :: 3.5
Classifier: Programming Language :: Python :: 3.6
Requires-Dist: requests
Requires-Dist: python-magic
